ewn/__init__.py
ewn/ewn.py
ewn/release.py
exin/__init__.py
exin/exin.py
exin/release.py
exin-0.1.0.dist-info/LICENSE
exin-0.1.0.dist-info/METADATA
exin-0.1.0.dist-info/WHEEL
exin-0.1.0.dist-info/top_level.txt
exin-0.1.0.dist-info/RECORD
