Metadata-Version: 2.1
Name: exin
Version: 0.1.0
Summary: Explore WordNet
Home-page: https://github.com/dinarior/explore_imagenet
Author: Or Dinari
Author-email: dinari@post.bgu.ac.il
License: MIT
Project-URL: Source, https://github.com/dinarior/explore_imagenet
Project-URL: Tracker, https://github.com/dinarior/explore_imagenet/issues
Project-URL: Documentation, https://github.com/dinarior/explore_imagenet
Keywords: julia python
Platform: UNKNOWN
Classifier: Development Status :: 4 - Beta
Classifier: License :: OSI Approved :: MIT License
Classifier: Programming Language :: Python :: 3
Classifier: Programming Language :: Python :: 3.4
Classifier: Programming Language :: Python :: 3.5
Classifier: Programming Language :: Python :: 3.6
Classifier: Programming Language :: Python :: 3.7
Classifier: Programming Language :: Python :: 3.8
Classifier: Programming Language :: Python :: 3.9
Requires-Dist: numpy
